nifty2/__init__.py
nifty2/nifty.py
niftygen2-2.1.1.dist-info/METADATA
niftygen2-2.1.1.dist-info/WHEEL
niftygen2-2.1.1.dist-info/top_level.txt
niftygen2-2.1.1.dist-info/RECORD
